tor_pykrx/NanumBarunGothic.ttf
tor_pykrx/__init__.py
tor_pykrx/bond/__init__.py
tor_pykrx/bond/bond.py
tor_pykrx/stock/__init__.py
tor_pykrx/stock/future_api.py
tor_pykrx/stock/stock_api.py
tor_pykrx/website/__init__.py
tor_pykrx/website/comm/__init__.py
tor_pykrx/website/comm/util.py
tor_pykrx/website/comm/webio.py
tor_pykrx/website/krx/__init__.py
tor_pykrx/website/krx/bond/__init__.py
tor_pykrx/website/krx/bond/core.py
tor_pykrx/website/krx/bond/ticker.py
tor_pykrx/website/krx/bond/wrap.py
tor_pykrx/website/krx/etx/__init__.py
tor_pykrx/website/krx/etx/core.py
tor_pykrx/website/krx/etx/ticker.py
tor_pykrx/website/krx/etx/wrap.py
tor_pykrx/website/krx/future/__init__.py
tor_pykrx/website/krx/future/core.py
tor_pykrx/website/krx/future/wrap.py
tor_pykrx/website/krx/krxio.py
tor_pykrx/website/krx/market/__init__.py
tor_pykrx/website/krx/market/core.py
tor_pykrx/website/krx/market/ticker.py
tor_pykrx/website/krx/market/wrap.py
tor_pykrx/website/naver/__init__.py
tor_pykrx/website/naver/core.py
tor_pykrx/website/naver/wrap.py
tor_pykrx-0.0.5.dist-info/LICENSE
tor_pykrx-0.0.5.dist-info/METADATA
tor_pykrx-0.0.5.dist-info/WHEEL
tor_pykrx-0.0.5.dist-info/RECORD
