Metadata-Version: 2.3
Name: tor-pykrx
Version: 0.0.5
Summary: tor-pykrx is a Python package for accessing the KRX (Korea Exchange) stock market data through the Tor network.
License: SEE LICENSE FILE
Author: minjun ju
Author-email: dev.mjun@gmail.com
Requires-Python: >=3.10,<4
Classifier: License :: Other/Proprietary License
Classifier: Programming Language :: Python :: 3
Classifier: Programming Language :: Python :: 3.10
Classifier: Programming Language :: Python :: 3.11
Classifier: Programming Language :: Python :: 3.12
Classifier: Programming Language :: Python :: 3.13
Classifier: Programming Language :: Python :: 3 :: Only
Requires-Dist: Deprecated (>=1.2.14,<2.0.0)
Requires-Dist: charset-normalizer (>=3.3.2,<4.0.0)
Requires-Dist: contourpy (>=1.2.1,<2.0.0)
Requires-Dist: cycler (>=0.12.1,<1.0.0)
Requires-Dist: fonttools (>=4.53.1,<5.0.0)
Requires-Dist: idna (>=3.7,<4.0.0)
Requires-Dist: kiwisolver (>=1.4.5,<2.0.0)
Requires-Dist: matplotlib (>=3.10.3,<4.0.0)
Requires-Dist: multipledispatch (>=1.0.0,<2.0.0)
Requires-Dist: numpy (>=2.0.0,<3.0.0)
Requires-Dist: packaging (>=24.1,<25.0)
Requires-Dist: pandas (>=2.2.2,<3.0.0)
Requires-Dist: pillow (>=10.4.0,<11.0.0)
Requires-Dist: pyparsing (>=3.1.2,<4.0.0)
Requires-Dist: python-dateutil (>=2.9.0.post0,<3.0.0)
Requires-Dist: pytz (>=2024.1,<2025.0)
Requires-Dist: requests (>=2.32.3,<3.0.0)
Requires-Dist: setuptools (>=80.8.0,<81.0.0)
Requires-Dist: six (>=1.16.0,<2.0.0)
Requires-Dist: tor-rq (==0.0.5)
Requires-Dist: tzdata (>=2024.1,<2025.0)
Requires-Dist: urllib3 (>=2.2.2,<3.0.0)
Requires-Dist: wrapt (>=1.16.0,<2.0.0)
Project-URL: Homepage, https://github.com/devmjun/tor-pykrx
Project-URL: Repository, https://github.com/devmjun/tor-pykrx
